traefik_cert_exporter/__about__.py
traefik_cert_exporter/__init__.py
traefik_cert_exporter/cli.py
traefik_cert_exporter/exceptions.py
traefik_cert_exporter/exporter.py
traefik_cert_exporter/handlers.py
traefik_cert_exporter/models.py
traefik_cert_exporter-1.0.1.dist-info/METADATA
traefik_cert_exporter-1.0.1.dist-info/WHEEL
traefik_cert_exporter-1.0.1.dist-info/entry_points.txt
traefik_cert_exporter-1.0.1.dist-info/licenses/LICENSE
traefik_cert_exporter-1.0.1.dist-info/RECORD
