Metadata-Version: 2.3
Name: traefik-cert-exporter
Version: 1.0.1
Summary: CLI and python library to export Traefik SSL certificates
Project-URL: Documentation, https://github.com/ahuahuachi/traefik-cert-exporter#readme
Project-URL: Issues, https://github.com/ahuahuachi/traefik-cert-exporter/issues
Project-URL: Source, https://github.com/ahuahuachi/traefik-cert-exporter
Author-email: Alfredo Altamirano <pypi.sprinkled287@passmail.net>
License-Expression: MIT
License-File: LICENSE
Keywords: certificate,cli,export,ssl,traefik
Classifier: Development Status :: 5 - Production/Stable
Classifier: License :: OSI Approved :: MIT License
Classifier: Programming Language :: Python
Classifier: Programming Language :: Python :: 3.10
Classifier: Programming Language :: Python :: 3.11
Classifier: Programming Language :: Python :: 3.12
Classifier: Topic :: Security
Classifier: Topic :: System :: Monitoring
Classifier: Topic :: Utilities
Requires-Python: >=3.10
Requires-Dist: click<9,>=8.1.7
Provides-Extra: dev
Requires-Dist: black; extra == 'dev'
Requires-Dist: isort; extra == 'dev'
Provides-Extra: tests
Requires-Dist: pytest; extra == 'tests'
